py_ng_deploy/.pyngdeployrc
py_ng_deploy/__init__.py
py_ng_deploy/__main__.py
py_ng_deploy/py_ng_build.py
py_ng_deploy/py_ng_upload.py
py_ng_deploy-0.0.14.dist-info/METADATA
py_ng_deploy-0.0.14.dist-info/WHEEL
py_ng_deploy-0.0.14.dist-info/entry_points.txt
py_ng_deploy-0.0.14.dist-info/top_level.txt
py_ng_deploy-0.0.14.dist-info/RECORD
