Metadata-Version: 2.1
Name: py-ng-deploy
Version: 0.0.14
Summary: Compile angular project and upload to sftp
Home-page: https://github.com/ccmorataya/py-ng-deploy
Author: Cristian Morataya
Author-email: cris.morataya@gmail.com
License: UNKNOWN
Platform: UNKNOWN
Classifier: Programming Language :: Python :: 3
Classifier: Programming Language :: Python :: 3.7
Requires-Dist: pysftp (>=0.2.9)
Requires-Dist: colorama
